hpestorapi/__init__.py
hpestorapi/base.py
hpestorapi/primera.py
hpestorapi/storeonce3.py
hpestorapi/storeonce3_utils.py
hpestorapi/storeonce4.py
hpestorapi/storeserv.py
hpestorapi/xp.py
hpestorapi-1.0.0.dist-info/LICENSE.txt
hpestorapi-1.0.0.dist-info/METADATA
hpestorapi-1.0.0.dist-info/WHEEL
hpestorapi-1.0.0.dist-info/top_level.txt
hpestorapi-1.0.0.dist-info/RECORD
