Metadata-Version: 2.1
Name: hpestorapi
Version: 1.0.0
Summary: python library that allows a simple way to use Rest API services for HPE storage and disk backup devices
Home-page: https://github.com/HewlettPackard/python-storage-clients
Author: Ivan Smirnov
Author-email: ivan.smirnov@hpe.com
Maintainer: Ivan Smirnov
Maintainer-email: ivan.smirnov@hpe.com
License: UNKNOWN
Keywords: HPE,REST,StoreOnce,3PAR,Primera,XP7,P9500,Storage array
Platform: UNKNOWN
Classifier: Development Status :: 4 - Beta
Classifier: Intended Audience :: Developers
Classifier: Topic :: Scientific/Engineering :: Interface Engine/Protocol Translator
Classifier: Topic :: Software Development :: Libraries :: Python Modules
Classifier: License :: OSI Approved :: Apache Software License
Classifier: Operating System :: OS Independent
Classifier: Programming Language :: Python
Classifier: Programming Language :: Python :: 3.6
Classifier: Programming Language :: Python :: 3.7
Classifier: Programming Language :: Python :: 3.8
Classifier: Programming Language :: Python :: Implementation :: CPython
Classifier: Programming Language :: Python :: Implementation :: PyPy
Requires-Python: <4,>=3.6
Requires-Dist: requests (<3,>=2.19.1)
